likee/__init__.py
likee/config.py
likee/likee.py
likee/utils.py
likee-0.0.13.dist-info/LICENSE
likee-0.0.13.dist-info/METADATA
likee-0.0.13.dist-info/WHEEL
likee-0.0.13.dist-info/top_level.txt
likee-0.0.13.dist-info/RECORD
